num2rank/__init__.py
num2rank/num2rank.py
num2rank-1.0.3.dist-info/METADATA
num2rank-1.0.3.dist-info/WHEEL
num2rank-1.0.3.dist-info/top_level.txt
num2rank-1.0.3.dist-info/RECORD
