Metadata-Version: 2.1
Name: num2rank
Version: 1.0.3
Summary: Converts integers (1, 2, 3) into ranks (1st, 2nd, 3rd)
Home-page: UNKNOWN
Author: AnnoyingRains
Author-email: <annoyingrain5@gmail.com>
License: UNKNOWN
Keywords: python,number,1st,2nd,3rd,1 to 1st,number converter,number suffix converter,number suffix
Platform: UNKNOWN
Classifier: Development Status :: 5 - Production/Stable
Classifier: Intended Audience :: Developers
Classifier: Programming Language :: Python :: 3
Classifier: Operating System :: Unix
Classifier: Operating System :: MacOS :: MacOS X
Classifier: Operating System :: Microsoft :: Windows
